{
  "id" : "GSM_NETWORK_DRILL_SUB_CAUSE_CODE_ANALYSIS_CELL",
  "name" : "AccessArea Sub Cause Code Analysis",
  "url" : "NETWORK/GSM/CALL_FAILURE_CAUSE_CODE_ANALYSIS/NETWORK_SUB_CAUSE_CODE_GRID",
  "params" : [ {
    "id" : "5",
    "queryParamName" : "node",
	"isTitleParam": "TRUE"
  }, {
    "id" : "2",
    "queryParamName" : "causeCodeDescription",
	"isTitleParam": "TRUE"
  }, {
    "id" : "6",
    "queryParamName" : "HIER3_ID"
  },{
    "id" : "CELL",
    "queryParamName" : "type",
    "isFixedVal" : "TRUE"
  }, {
    "id" : "1",
    "queryParamName" : "causeCode"
  }],
  "style" : "analysisCausecode",
  "windowType" : "GRID",
  "isEnabled" : "TRUE",
  "toolBarType" : "TOOLBAR1",
  "display" : "grid"
}

